[
  {
    "name": "Qinhong Zhou",
    "photo": "phd_qinhong.png",
    "institution": "University of Massachusetts Amherst",
    "url": "https://zhouqqhh.github.io/"
  },
  {
    "name": "Hongxin Zhang",
    "photo": "phd_hongxin.jpg",
    "institution": "University of Massachusetts Amherst",
    "url": "https://icefoxzhx.github.io/"
  },
  {
    "name": "Xiangye Lin",
    "photo": "placeholder.jpg",
    "institution": "University of Massachusetts Amherst"
  },
  {
    "name": "Zheyuan Zhang",
    "photo": "zheyuan_zhang.jpg",
    "institution": "Johns Hopkins University"
  },
  {
    "name": "Yutian Chen",
    "photo": "yutian_chen.jpg",
    "institution": "Carnegie Mellon University"
  },
  {
    "name": "Wenjun Liu",
    "photo": "ms_wenjun.png",
    "institution": "University of Massachusetts Amherst"
  },
  {
    "name": "Jincheng Yang",
    "photo": "placeholder.jpg",
    "institution": "University of Massachusetts Amherst"
  },
  {
    "name": "Sunli Chen",
    "photo": "phd_sunli.png",
    "institution": "University of Massachusetts Amherst",
    "url": "https://eeeeeerickkk.github.io/"
  },
  {
    "name": "Lixing Fang",
    "photo": "phd_lixing.jpg",
    "institution": "University of Massachusetts Amherst",
    "url": "https://owenowl.github.io/"
  },
  {
    "name": "Xinyu Sun",
    "photo": "xinyu_sun.jpg",
    "institution": "Tencent Robotics X Lab"
  },
  {
    "name": "Zeyuan Wang",
    "photo": "zeyuan_wang.jpg",
    "institution": "University of Massachusetts Amherst"
  },
  {
    "name": "Zunzhe Zhang",
    "photo": "zunzhe_zhang.jpg",
    "institution": "University of Massachusetts Amherst"
  },
  {
    "name": "Daksha Ladia",
    "photo": "daksha_ladia.jpg",
    "institution": "University of Massachusetts Amherst"
  },
  {
    "name": "Jiageng Liu",
    "photo": "ms_jiageng.png",
    "institution": "University of Massachusetts Amherst"
  },
  {
    "name": "Zhehuan Chen",
    "photo": "ms_zhehuan.png",
    "institution": "University of Massachusetts Amherst",
    "url": "https://acmlczh.github.io/"
  },
  {
    "name": "Bao Chi Dang",
    "photo": "bs_bao.jpg",
    "institution": "University of Massachusetts Amherst",
    "url": "https://github.com/weebao"
  }
] 